bewspweb/__init__.py
bewspweb/bewspweb_print.py
bewspweb/bewspweb_start.py
bewspweb/bewspweb_weave.py
test/test.py
test/test_1.py
test/test_2.py
bewspweb-0.1.3.dist-info/METADATA
bewspweb-0.1.3.dist-info/WHEEL
bewspweb-0.1.3.dist-info/top_level.txt
bewspweb-0.1.3.dist-info/RECORD
