Metadata-Version: 2.1
Name: bewspweb
Version: 0.1.3
Summary: Functions to extract data from a web page using selenium webdriver with not too much code.
Home-page: https://github.com/marceloandrade93/bewspweb
Author: Marcelo Andrade
Author-email: andradeswork@gmail.com
License: MIT License
Classifier: Programming Language :: Python :: 3
Classifier: License :: OSI Approved :: MIT License
Classifier: Operating System :: OS Independent
Requires-Python: >=3.6
Requires-Dist: selenium
Requires-Dist: webdriver-manager
